hb/__init__.py
hb/__main__.py
ohos_build-0.4.6.dist-info/LICENSE
ohos_build-0.4.6.dist-info/METADATA
ohos_build-0.4.6.dist-info/WHEEL
ohos_build-0.4.6.dist-info/entry_points.txt
ohos_build-0.4.6.dist-info/top_level.txt
ohos_build-0.4.6.dist-info/RECORD
