Metadata-Version: 2.1
Name: ohos-build
Version: 0.4.6
Summary: OHOS build command line tool
Home-page: https://gitee.com/openharmony/build_lite
Author: Huawei
Author-email: contact@openharmony.io
License: Apache 2.0
Platform: UNKNOWN
Requires-Python: >=3.7
Requires-Dist: PyYAML
Requires-Dist: kconfiglib (>=14.1.0)
Requires-Dist: prompt-toolkit (==1.0.14)
Requires-Dist: requests
